Metadata-Version: 1.1
Name: qautils
Version: 0.0.2
Summary: QA utils library provides methods compatibility with all python versions
Home-page: https://github.com/netzulo/qautils
Author: Netzulo SQA developer
Author-email: netzuleando@gmail.com
License:                     GNU AFFERO GENERAL PUBLIC LICENSE
